{"cameraMode":{"drawMode":0,"name":"Shaded","section":"Shading Mode"},"sceneLighting":false,"audioPlay":false,"sceneViewState":{"showFog":true,"showMaterialUpdate":false,"showSkybox":false,"showFlares":true,"showImageEffects":true,"showParticleSystems":true,"showVisualEffectGraphs":true,"m_FxEnabled":true},"in2DMode":false,"pivot":{"x":-0.864514946937561,"y":-3.45894718170166,"z":-2.389436721801758},"rotation":{"x":0.04361826553940773,"y":-0.8758391737937927,"z":0.4738188087940216,"w":0.08062458783388138},"size":4.662535667419434,"orthographic":false}